riot/__init__.py
riot/__main__.py
riot/cli.py
riot/py.typed
riot/riot.py
riot-0.20.1.dist-info/LICENSE.apache2
riot-0.20.1.dist-info/METADATA
riot-0.20.1.dist-info/NOTICE
riot-0.20.1.dist-info/WHEEL
riot-0.20.1.dist-info/entry_points.txt
riot-0.20.1.dist-info/top_level.txt
riot-0.20.1.dist-info/RECORD
