Metadata-Version: 2.1
Name: riot
Version: 0.20.1
Summary: A simple Python test runner runner.
Home-page: https://github.com/DataDog/riot
Author: Datadog, Inc.
Author-email: dev@datadoghq.com
License: Apache 2
Classifier: Programming Language :: Python
Classifier: Programming Language :: Python :: 3.7
Classifier: Programming Language :: Python :: 3.8
Classifier: Programming Language :: Python :: 3.9
Classifier: Programming Language :: Python :: 3.10
Classifier: Programming Language :: Python :: 3.11
Classifier: Programming Language :: Python :: 3.12
Requires-Python: >=3.7
License-File: LICENSE.apache2
License-File: NOTICE
Requires-Dist: click >=7
Requires-Dist: virtualenv <=20.26.6
Requires-Dist: rich
Requires-Dist: pexpect
Requires-Dist: packaging
Requires-Dist: dataclasses ; python_version < "3.7"
Requires-Dist: setuptools ; python_version >= "3.12"
